group_terminal/__init__.py
group_terminal/client.py
group_terminal/server.py
group_terminal/terminal.py
group_terminal-0.0.2.dist-info/METADATA
group_terminal-0.0.2.dist-info/WHEEL
group_terminal-0.0.2.dist-info/licenses/LICENSE
group_terminal-0.0.2.dist-info/RECORD
