Metadata-Version: 2.4
Name: group-terminal
Version: 0.0.2
Summary: Group Terminal
Author-email: Martin Krasser <martin@gradion.ai>
License-Expression: Apache-2.0
License-File: LICENSE
Requires-Python: <3.15,>=3.11
Requires-Dist: fastapi>=0.119.1
Requires-Dist: rich>=14.2.0
Requires-Dist: uvicorn>=0.38.0
Requires-Dist: websockets>=15.0.1
